MANIFEST.in
MIT-LICENSE
setup.py
docs/Makefile
docs/source/conf.py
docs/source/index.rst
docs/source/assets/index.rst
docs/source/assets/reference.rst
docs/source/cache/index.rst
docs/source/cache/reference.rst
docs/source/cms/index.rst
docs/source/cms/reference.rst
docs/source/cms/scarletvsdjangoadmin.rst
docs/source/cms/tutorial.rst
docs/source/versioning/index.rst
docs/source/versioning/reference.rst
samples/cache/functionview/__init__.py
samples/cache/functionview/models.py
samples/cache/functionview/urls.py
samples/cache/functionview/views.py
scarlet/__init__.py
scarlet.egg-info/PKG-INFO
scarlet.egg-info/SOURCES.txt
scarlet.egg-info/dependency_links.txt
scarlet.egg-info/requires.txt
scarlet.egg-info/top_level.txt
scarlet/accounts/__init__.py
scarlet/accounts/apps.py
scarlet/accounts/cms_bundles.py
scarlet/accounts/forms.py
scarlet/accounts/groups.py
scarlet/accounts/models.py
scarlet/accounts/settings.py
scarlet/accounts/views.py
scarlet/accounts/management/__init__.py
scarlet/assets/__init__.py
scarlet/assets/apps.py
scarlet/assets/cms_bundles.py
scarlet/assets/crops.py
scarlet/assets/fields.py
scarlet/assets/forms.py
scarlet/assets/managers.py
scarlet/assets/models.py
scarlet/assets/renders.py
scarlet/assets/settings.py
scarlet/assets/signals.py
scarlet/assets/tasks.py
scarlet/assets/utils.py
scarlet/assets/views.py
scarlet/assets/widgets.py
scarlet/assets/management/__init__.py
scarlet/assets/management/commands/__init__.py
scarlet/assets/management/commands/cleanup_assets.py
scarlet/assets/management/commands/sync-denormalized-fields.py
scarlet/assets/management/commands/update_model_tags.py
scarlet/assets/migrations/0001_initial.py
scarlet/assets/migrations/__init__.py
scarlet/assets/templates/assets/asset_uploaded.html
scarlet/assets/templates/assets/asset_widget.html
scarlet/assets/templates/assets/crop.html
scarlet/assets/templates/assets/edit.html
scarlet/cache/__init__.py
scarlet/cache/admin.py
scarlet/cache/apps.py
scarlet/cache/decorators.py
scarlet/cache/groups.py
scarlet/cache/manager.py
scarlet/cache/router.py
scarlet/cache/views.py
scarlet/cms/__init__.py
scarlet/cms/actions.py
