Metadata-Version: 1.1
Name: scarlet
Version: 1.2.4
Summary: A replacement for the Django Admin, focused on Content Management
Home-page: http://github.com/ff0000/scarlet/
Author: RED Interactive Agency
Author-email: geeks@ff0000.com
License: MIT
Platform: UNKNOWN
Classifier: Development Status :: 4 - Beta
Classifier: Environment :: Web Environment
Classifier: Framework :: Django
Classifier: Intended Audience :: Developers
Classifier: License :: OSI Approved :: MIT License
Classifier: Operating System :: POSIX
Classifier: Programming Language :: Python
